nion/nionui_tool/__init__.py
nion/nionui_tool/command.py
nionui_tool-5.1.5.data/data/Scripts/NionUILauncher/D3Dcompiler_47.dll
nionui_tool-5.1.5.data/data/Scripts/NionUILauncher/NionUILauncher.exe
nionui_tool-5.1.5.data/data/Scripts/NionUILauncher/Qt6Core.dll
nionui_tool-5.1.5.data/data/Scripts/NionUILauncher/Qt6Gui.dll
nionui_tool-5.1.5.data/data/Scripts/NionUILauncher/Qt6Network.dll
nionui_tool-5.1.5.data/data/Scripts/NionUILauncher/Qt6Svg.dll
nionui_tool-5.1.5.data/data/Scripts/NionUILauncher/Qt6Widgets.dll
nionui_tool-5.1.5.data/data/Scripts/NionUILauncher/bootstrap.py
nionui_tool-5.1.5.data/data/Scripts/NionUILauncher/dxcompiler.dll
nionui_tool-5.1.5.data/data/Scripts/NionUILauncher/dxil.dll
nionui_tool-5.1.5.data/data/Scripts/NionUILauncher/stylesheet.qss
nionui_tool-5.1.5.data/data/Scripts/NionUILauncher/Graphics/WinIcon.ico
nionui_tool-5.1.5.data/data/Scripts/NionUILauncher/Graphics/scroll_bg.png
nionui_tool-5.1.5.data/data/Scripts/NionUILauncher/Graphics/scroll_bg_horizontal.png
nionui_tool-5.1.5.data/data/Scripts/NionUILauncher/Graphics/scroll_gem.png
nionui_tool-5.1.5.data/data/Scripts/NionUILauncher/Graphics/scroll_gem_horizontal.png
nionui_tool-5.1.5.data/data/Scripts/NionUILauncher/Graphics/scroll_gem_horizontal_hover.png
nionui_tool-5.1.5.data/data/Scripts/NionUILauncher/Graphics/scroll_gem_hover.png
nionui_tool-5.1.5.data/data/Scripts/NionUILauncher/generic/qtuiotouchplugin.dll
nionui_tool-5.1.5.data/data/Scripts/NionUILauncher/iconengines/qsvgicon.dll
nionui_tool-5.1.5.data/data/Scripts/NionUILauncher/imageformats/qgif.dll
nionui_tool-5.1.5.data/data/Scripts/NionUILauncher/imageformats/qico.dll
nionui_tool-5.1.5.data/data/Scripts/NionUILauncher/imageformats/qjpeg.dll
nionui_tool-5.1.5.data/data/Scripts/NionUILauncher/imageformats/qsvg.dll
nionui_tool-5.1.5.data/data/Scripts/NionUILauncher/networkinformation/qnetworklistmanager.dll
nionui_tool-5.1.5.data/data/Scripts/NionUILauncher/platforms/qwindows.dll
nionui_tool-5.1.5.dist-info/licenses/LICENSE
nionui_tool-5.1.5.dist-info/licenses/NOTICES
nionui_tool-5.1.5.dist-info/METADATA
nionui_tool-5.1.5.dist-info/WHEEL
nionui_tool-5.1.5.dist-info/entry_points.txt
nionui_tool-5.1.5.dist-info/top_level.txt
nionui_tool-5.1.5.dist-info/RECORD
